pycozo/__init__.py
pycozo/builder.py
pycozo/client.py
pycozo/client_patch.py
pycozo/ext_impl.py
pycozo/ipyext.py
pycozo/ipyext_direct.py
pycozo/test_builder.py
pycozo/test_client.py
pycozo-0.7.6.dist-info/LICENSE.txt
pycozo-0.7.6.dist-info/METADATA
pycozo-0.7.6.dist-info/WHEEL
pycozo-0.7.6.dist-info/top_level.txt
pycozo-0.7.6.dist-info/RECORD
