Metadata-Version: 2.1
Name: pycozo
Version: 0.7.6
Summary: Python client for the Cozo database
Home-page: 
Author: Ziyang Hu
Author-email: hu.ziyang@cantab.net
License: MPL-2.0
Classifier: Development Status :: 3 - Alpha
Classifier: Intended Audience :: Developers
Classifier: Framework :: IPython
Classifier: Programming Language :: Python
Classifier: Topic :: Utilities
Provides-Extra: pandas
Provides-Extra: embedded
Provides-Extra: client
License-File: LICENSE.txt
